peachy/PC.py
peachy/__init__.py
peachy/__main__.py
peachy/audio.py
peachy/base.py
peachy/collision.py
peachy/config.py
peachy/etc.py
peachy/fs.py
peachy/geo.py
peachy/graphics.py
peachy/resources.py
peachy/stage.py
peachy/ui.py
peachy/utils.py
peachy-0.1.0.dist-info/DESCRIPTION.rst
peachy-0.1.0.dist-info/METADATA
peachy-0.1.0.dist-info/RECORD
peachy-0.1.0.dist-info/WHEEL
peachy-0.1.0.dist-info/metadata.json
peachy-0.1.0.dist-info/top_level.txt
