Metadata-Version: 2.0
Name: peachy
Version: 0.1.0
Summary: A python3 game development framework
Home-page: https://github.com/shellbotx/peachy
Author: Sheldon Allen (shellbot)
Author-email: studio.shellbot@gmail.com
License: MIT
Keywords: peachy pygame gamedev game gaming development 2d graphics
Platform: UNKNOWN
Classifier: Development Status :: 4 - Beta
Classifier: Intended Audience :: Developers
Classifier: License :: OSI Approved :: MIT License
Classifier: Natural Language :: English
Classifier: Operating System :: OS Independent
Classifier: Programming Language :: Python
Classifier: Programming Language :: Python :: 3.5
Classifier: Topic :: Documentation :: Sphinx
Classifier: Topic :: Games/Entertainment
Classifier: Topic :: Multimedia :: Graphics
Classifier: Topic :: Software Development :: Libraries :: Application Frameworks
Classifier: Topic :: Software Development :: Libraries :: pygame
Classifier: Topic :: Software Development :: Libraries :: Python Modules
Requires-Dist: pygame
Requires-Dist: pytmx
